django_axe/.DS_Store
django_axe/__init__.py
django_axe/apps.py
django_axe/asgi.py
django_axe/media/django_axe/.DS_Store
django_axe/media/django_axe_report.json
django_axe/reports/__init__.py
django_axe/reports/apps.py
django_axe/reports/report.py
django_axe/reports/urls.py
django_axe/reports/views.py
django_axe/settings.py
django_axe/static/django_axe/css/main.css
django_axe/static/django_axe/css/style.css
django_axe/static/django_axe/css/style.css.map
django_axe/static/django_axe/images/bottom.svg
django_axe/static/django_axe/images/hero.png
django_axe/static/django_axe/images/top.svg
django_axe/static/django_axe/js/highlight.js
django_axe/static/django_axe/js/highlight.js.map
django_axe/static/django_axe/js/main.js
django_axe/static/django_axe/js/main.js.map
django_axe/templates/base.html
django_axe/templates/django_axe/list_card.html
django_axe/templates/django_axe/list_table.html
django_axe/templates/django_axe/report.html
django_axe/templates/django_axe/script.html
django_axe/templatetags/__init__.py
django_axe/templatetags/django_axe.py
django_axe/urls.py
django_axe/views.py
django_axe/wsgi.py
django_axe-0.5.22.dist-info/METADATA
django_axe-0.5.22.dist-info/WHEEL
django_axe-0.5.22.dist-info/RECORD
