Metadata-Version: 2.1
Name: django-axe
Version: 0.5.22
Summary: 
Author: Brahma Dutta Upadhyay
Author-email: brahmaduttau@kpmg.com
Requires-Python: >=3.10,<4.0
Classifier: Programming Language :: Python :: 3
Classifier: Programming Language :: Python :: 3.10
Classifier: Programming Language :: Python :: 3.11
Classifier: Programming Language :: Python :: 3.12
Requires-Dist: django (>=4.2.9,<5.0.0)
Requires-Dist: djlint (>=1.34.1,<2.0.0)
Requires-Dist: ruff (>=0.5.3,<0.6.0)
